codexpp/__init__.py
codexpp/__main__.py
codexpp/cli.py
codexpp/config.py
codexpp/loader.py
codexpp/models.py
codexpp/resources/__init__.py
codexpp/resources/command_packs/__init__.py
codexpp/resources/commands/__init__.py
codexpp/resources/commands/default.toml
codexpp/resources/mcp/__init__.py
codexpp/resources/mcp/default.toml
codexpp/resources/personas/__init__.py
codexpp/resources/prompts/__init__.py
codexpp/resources/prompts/default/__init__.py
codexpp/resources/prompts/default/cx-analyze.md
codexpp/resources/prompts/default/cx-brainstorm.md
codexpp/resources/prompts/default/cx-deploy.md
codexpp/resources/prompts/default/cx-doc.md
codexpp/resources/prompts/default/cx-implement.md
codexpp/resources/prompts/default/cx-plan.md
codexpp/resources/prompts/default/cx-review.md
codexpp/resources/prompts/default/cx-rollback.md
codexpp/resources/prompts/default/cx-security.md
codexpp/resources/prompts/default/cx-status.md
codexpp/resources/prompts/default/cx-test.md
codexpp-0.4.2.dist-info/licenses/LICENSE
codexpp-0.4.2.dist-info/METADATA
codexpp-0.4.2.dist-info/WHEEL
codexpp-0.4.2.dist-info/entry_points.txt
codexpp-0.4.2.dist-info/top_level.txt
codexpp-0.4.2.dist-info/RECORD
