Metadata-Version: 2.4
Name: codexpp
Version: 0.4.2
Summary: Persona-driven command pack and MCP setup for Codex CLI
Author-email: avometre <ohmkanunu1923@gmail.com>
License-Expression: MIT
Project-URL: Homepage, https://github.com/avometre/codexpp
Project-URL: Repository, https://github.com/avometre/codexpp
Project-URL: Issues, https://github.com/avometre/codexpp/issues
Keywords: codex,cli,ai,development,framework,mcp,prompts,codex-cli
Classifier: Development Status :: 3 - Alpha
Classifier: Intended Audience :: Developers
Classifier: Environment :: Console
Classifier: Operating System :: OS Independent
Classifier: Programming Language :: Python :: 3
Classifier: Programming Language :: Python :: 3.11
Classifier: Programming Language :: Python :: 3.12
Classifier: Programming Language :: Python :: 3.13
Classifier: Topic :: Software Development :: Build Tools
Requires-Python: >=3.11
License-File: LICENSE
Dynamic: license-file
